arp_jarvis_daemon/__init__.py
arp_jarvis_daemon/cli.py
arp_jarvis_daemon/config.py
arp_jarvis_daemon/daemon.py
arp_jarvis_daemon/errors.py
arp_jarvis_daemon/instance_manager.py
arp_jarvis_daemon/instance_store.py
arp_jarvis_daemon/run_router.py
arp_jarvis_daemon/run_store.py
arp_jarvis_daemon/runtime_process.py
arp_jarvis_daemon/runtime_profiles.py
arp_jarvis_daemon/server.py
arp_jarvis_daemon/types.py
arp_jarvis_daemon-0.1.0.dist-info/licenses/LICENSE
arp_jarvis_daemon-0.1.0.dist-info/METADATA
arp_jarvis_daemon-0.1.0.dist-info/WHEEL
arp_jarvis_daemon-0.1.0.dist-info/entry_points.txt
arp_jarvis_daemon-0.1.0.dist-info/top_level.txt
arp_jarvis_daemon-0.1.0.dist-info/RECORD
