Metadata-Version: 2.4
Name: arp-jarvis-daemon
Version: 0.1.0
Summary: Jarvis Daemon core library for managing ARP runtime instances.
Author: Agent Runtime Protocol
License: MIT License
Requires-Python: >=3.10
License-File: LICENSE
Requires-Dist: arp-standard-py<0.2.0,>=0.1.0
Requires-Dist: fastapi>=0.115
Requires-Dist: uvicorn>=0.30
Provides-Extra: dev
Requires-Dist: pytest>=7; extra == "dev"
Requires-Dist: pytest-cov>=4; extra == "dev"
Requires-Dist: pyright>=1.1.0; extra == "dev"
Dynamic: license-file
